classifier.py
pystmm/__init__.py
pystmm/classifier.py
pystmm/utils/__init__.py
pystmm/utils/data.py
pystmm-0.1.0.dist-info/DESCRIPTION.rst
pystmm-0.1.0.dist-info/METADATA
pystmm-0.1.0.dist-info/RECORD
pystmm-0.1.0.dist-info/WHEEL
pystmm-0.1.0.dist-info/metadata.json
pystmm-0.1.0.dist-info/top_level.txt
